odoo/addons/shopfloor_delivery_shipment_mobile/README.rst
odoo/addons/shopfloor_delivery_shipment_mobile/__init__.py
odoo/addons/shopfloor_delivery_shipment_mobile/__manifest__.py
odoo/addons/shopfloor_delivery_shipment_mobile/i18n/it.po
odoo/addons/shopfloor_delivery_shipment_mobile/i18n/shopfloor_delivery_shipment_mobile.pot
odoo/addons/shopfloor_delivery_shipment_mobile/readme/CONTRIBUTORS.rst
odoo/addons/shopfloor_delivery_shipment_mobile/readme/DESCRIPTION.rst
odoo/addons/shopfloor_delivery_shipment_mobile/static/description/icon.png
odoo/addons/shopfloor_delivery_shipment_mobile/static/description/index.html
odoo/addons/shopfloor_delivery_shipment_mobile/static/wms/src/demo/demo.delivery_shipment.js
odoo/addons/shopfloor_delivery_shipment_mobile/static/wms/src/scenario/delivery_shipment.js
odoo/addons/shopfloor_delivery_shipment_mobile/templates/assets.xml
odoo13_addon_shopfloor_delivery_shipment_mobile-13.0.1.0.1.dev4.dist-info/METADATA
odoo13_addon_shopfloor_delivery_shipment_mobile-13.0.1.0.1.dev4.dist-info/WHEEL
odoo13_addon_shopfloor_delivery_shipment_mobile-13.0.1.0.1.dev4.dist-info/top_level.txt
odoo13_addon_shopfloor_delivery_shipment_mobile-13.0.1.0.1.dev4.dist-info/RECORD
