Metadata-Version: 2.1
Name: odoo13-addon-shopfloor-delivery-shipment-mobile
Version: 13.0.1.0.1.dev4
Summary: Frontend for delivery shipment scenario for shopfloor
Home-page: https://github.com/OCA/wms
Author: Camptocamp, Odoo Community Association (OCA)
Author-email: support@odoo-community.org
License: AGPL-3
Platform: UNKNOWN
Classifier: Programming Language :: Python
Classifier: Framework :: Odoo
Classifier: Framework :: Odoo :: 13.0
Classifier: License :: OSI Approved :: GNU Affero General Public License v3
Classifier: Development Status :: 3 - Alpha
Requires-Python: >=3.5
Requires-Dist: odoo13-addon-shopfloor-delivery-shipment
Requires-Dist: odoo13-addon-shopfloor-mobile
Requires-Dist: odoo <13.1dev,>=13.0a
